odoo/addons/event_email_reminder/README.rst
odoo/addons/event_email_reminder/__init__.py
odoo/addons/event_email_reminder/__manifest__.py
odoo/addons/event_email_reminder/data/event_email_reminder_data.xml
odoo/addons/event_email_reminder/i18n/es.po
odoo/addons/event_email_reminder/models/__init__.py
odoo/addons/event_email_reminder/models/event.py
odoo/addons/event_email_reminder/readme/CONFIGURE.rst
odoo/addons/event_email_reminder/readme/CONTRIBUTORS.rst
odoo/addons/event_email_reminder/readme/CREDITS.rst
odoo/addons/event_email_reminder/readme/DESCRIPTION.rst
odoo/addons/event_email_reminder/static/description/icon.png
odoo/addons/event_email_reminder/static/description/index.html
odoo/addons/event_email_reminder/tests/__init__.py
odoo/addons/event_email_reminder/tests/test_event_event.py
odoo12_addon_event_email_reminder-12.0.1.0.0.dist-info/METADATA
odoo12_addon_event_email_reminder-12.0.1.0.0.dist-info/RECORD
odoo12_addon_event_email_reminder-12.0.1.0.0.dist-info/WHEEL
odoo12_addon_event_email_reminder-12.0.1.0.0.dist-info/top_level.txt
